virtuals_sdk/__init__.py
virtuals_sdk/game/README.md
virtuals_sdk/game/__init__.py
virtuals_sdk/game/agent.py
virtuals_sdk/game/custom_types.py
virtuals_sdk/game/utils.py
virtuals_sdk/game/worker.py
virtuals_sdk/twitter_agent/README.md
virtuals_sdk/twitter_agent/__init__.py
virtuals_sdk/twitter_agent/agent.py
virtuals_sdk/twitter_agent/sdk.py
virtuals_sdk/twitter_agent/functions/__init__.py
virtuals_sdk/twitter_agent/functions/discord.py
virtuals_sdk/twitter_agent/functions/farcaster.py
virtuals_sdk/twitter_agent/functions/telegram.py
virtuals_sdk-0.1.6.dist-info/METADATA
virtuals_sdk-0.1.6.dist-info/WHEEL
virtuals_sdk-0.1.6.dist-info/RECORD
