Metadata-Version: 2.4
Name: virtuals-sdk
Version: 0.1.6
Summary: Official Python SDK for Virtuals API/GAME
Project-URL: Homepage, https://github.com/Virtual-Protocol/virtuals-python
Project-URL: Bug Tracker, https://github.com/Virtual-Protocol/virtuals-python/issues
Author-email: Your Name <your.email@example.com>
Classifier: Development Status :: 3 - Alpha
Classifier: Intended Audience :: Developers
Classifier: License :: OSI Approved :: MIT License
Classifier: Operating System :: OS Independent
Classifier: Programming Language :: Python :: 3
Classifier: Programming Language :: Python :: 3.8
Classifier: Programming Language :: Python :: 3.9
Classifier: Programming Language :: Python :: 3.10
Classifier: Programming Language :: Python :: 3.11
Classifier: Topic :: Software Development :: Libraries :: Python Modules
Requires-Python: >=3.8
Requires-Dist: requests>=2.26.0
Requires-Dist: typing-extensions>=4.0.0
